vl_search_ml_client/__init__.py
vl_search_ml_client-0.0.1.dist-info/METADATA
vl_search_ml_client-0.0.1.dist-info/WHEEL
vl_search_ml_client-0.0.1.dist-info/top_level.txt
vl_search_ml_client-0.0.1.dist-info/RECORD
