Metadata-Version: 2.4
Name: vl-search-ml-client
Version: 0.0.1
Summary: Reserved package name - not yet available for use
Author: Package Maintainer
License: Proprietary
Project-URL: Homepage, https://github.com/placeholder/vl-search-ml-client
Classifier: Development Status :: 1 - Planning
Classifier: Intended Audience :: Developers
Classifier: Programming Language :: Python :: 3
Classifier: Programming Language :: Python :: 3.8
Classifier: Programming Language :: Python :: 3.9
Classifier: Programming Language :: Python :: 3.10
Classifier: Programming Language :: Python :: 3.11
Classifier: Programming Language :: Python :: 3.12
Classifier: Programming Language :: Python :: 3.13
Requires-Python: >=3.8
